CommcareTranslationChecker/CommcareTranslationChecker.py
CommcareTranslationChecker/__init__.py
CommcareTranslationChecker/exceptions.py
CommcareTranslationChecker-0.9.3.5.dist-info/DESCRIPTION.rst
CommcareTranslationChecker-0.9.3.5.dist-info/METADATA
CommcareTranslationChecker-0.9.3.5.dist-info/RECORD
CommcareTranslationChecker-0.9.3.5.dist-info/WHEEL
CommcareTranslationChecker-0.9.3.5.dist-info/entry_points.txt
CommcareTranslationChecker-0.9.3.5.dist-info/metadata.json
CommcareTranslationChecker-0.9.3.5.dist-info/top_level.txt
