Metadata-Version: 2.0
Name: CommcareTranslationChecker
Version: 0.9.3.5
Summary: Command line tool to check that Bulk Translation files for CommCare apps have consistent <output value.../> tags across translations.
Home-page: https://github.com/dimagi/CommcareTranslationChecker
Author: Dimagi
Author-email: information@dimagi.com
License: MIT
Keywords: c,o,m,m,c,a,r,e, ,d,i,m,a,g,i
Platform: UNKNOWN
Classifier: Development Status :: 4 - Beta
Classifier: Intended Audience :: Developers
Classifier: Intended Audience :: Customer Service
Classifier: Topic :: Utilities
Classifier: License :: OSI Approved :: MIT License
Classifier: Programming Language :: Python :: 2
Classifier: Programming Language :: Python :: 2.7
Classifier: Programming Language :: Python :: 3
Classifier: Programming Language :: Python :: 3.6
Requires-Dist: openpyxl (>=2.6.1)
